src/__init__.py
src/main.py
canvasTodoist-0.0.5.dist-info/LICENSE
canvasTodoist-0.0.5.dist-info/METADATA
canvasTodoist-0.0.5.dist-info/WHEEL
canvasTodoist-0.0.5.dist-info/entry_points.txt
canvasTodoist-0.0.5.dist-info/top_level.txt
canvasTodoist-0.0.5.dist-info/RECORD
